setup.py
build/lib/common_lib_zxwqxtu/__init__.py
build/lib/common_lib_zxwqxtu/fun.py
build/lib/common_lib_zxwqxtu/xhttp.py
common_lib_zxwqxtu/__init__.py
common_lib_zxwqxtu/fun.py
common_lib_zxwqxtu/xhttp.py
common_lib_zxwqxtu-0.0.3.dist-info/LICENSE
common_lib_zxwqxtu-0.0.3.dist-info/METADATA
common_lib_zxwqxtu-0.0.3.dist-info/WHEEL
common_lib_zxwqxtu-0.0.3.dist-info/top_level.txt
common_lib_zxwqxtu-0.0.3.dist-info/RECORD
