Metadata-Version: 2.1
Name: common_lib_zxwqxtu
Version: 0.0.3
Summary: A small example package
Author-email: zxwqxtu <zxwqxtu@outlook.com>
Project-URL: Homepage, https://github.com/zxwqxtu/common_lib_py
Project-URL: Issues, https://github.com/zxwqxtu/common_lib_py/issues
Classifier: Programming Language :: Python :: 3
Classifier: License :: OSI Approved :: MIT License
Classifier: Operating System :: OS Independent
Requires-Python: >=3.6
License-File: LICENSE
